chimera/__init__.py
chimera/bibtex.py
chimera/constants.py
chimera/convert.py
chimera/editList.py
chimera/getchimera.py
chimera/objects.py
chimera/parser_h1.py
chimera/protocols.conf
chimera/utils.py
chimera/wizards.py
chimera/Bundles/scipion/bundle_info.xml
chimera/Bundles/scipion/src/__init__.py
chimera/Bundles/scipion/src/api.py
chimera/Bundles/scipion/src/cmd.py
chimera/Bundles/scipion/src/constants.py
chimera/Bundles/scipion/src/docs/user/commands/scipion.html
chimera/Bundles/scipion/src/docs/user/commands/scipioncombine.html
chimera/Bundles/scipion/src/docs/user/commands/scipionrs.html
chimera/Bundles/scipion/src/docs/user/commands/scipionshell.html
chimera/Bundles/scipion/src/docs/user/commands/scipionshellcrown.html
chimera/Bundles/scipion/src/docs/user/commands/scipionss.html
chimera/Bundles/scipion/src/docs/user/commands/scipionwrite.html
chimera/colabs/browser.py
chimera/colabs/chimera_alphafold21_colab.ipynb
chimera/colabs/chimera_alphafold_colab.ipynb
chimera/colabs/click.py
chimera/colabs/down.py
chimera/colabs/kk.colab
chimera/colabs/kk.ipynb
chimera/colabs/mouse.py
chimera/colabs/phenix_alphafold_colab.ipynb
chimera/colabs/test_colab.ipynb
chimera/protocols/__init__.py
chimera/protocols/protocol_alphafold.py
chimera/protocols/protocol_base.py
chimera/protocols/protocol_contacts.py
chimera/protocols/protocol_fit.py
chimera/protocols/protocol_modeller_search.py
chimera/protocols/protocol_operate.py
chimera/protocols/protocol_restore.py
chimera/protocols/protocol_subtraction_maps.py
chimera/tests/__init__.py
chimera/tests/test_alpha_fold.py
chimera/tests/test_objects.py
chimera/tests/test_protocol_chimera_fit.py
chimera/tests/test_protocol_chimera_map_subtraction.py
chimera/tests/test_protocol_chimera_operate.py
chimera/tests/test_protocol_contact.py
chimera/tests/test_protocol_modeller_search.py
chimera/viewers/__init__.py
chimera/viewers/viewer.py
chimera/viewers/viewer_contacts.py
scipion_em_chimera-3.4.1.dist-info/LICENSE
scipion_em_chimera-3.4.1.dist-info/METADATA
scipion_em_chimera-3.4.1.dist-info/WHEEL
scipion_em_chimera-3.4.1.dist-info/entry_points.txt
scipion_em_chimera-3.4.1.dist-info/top_level.txt
scipion_em_chimera-3.4.1.dist-info/RECORD
