Metadata-Version: 2.1
Name: scipion-em-chimera
Version: 3.4.1
Summary: Plugin to use chimera programs within the Scipion framework
Home-page: https://github.com/scipion-em/scipion-em-chimera
Author: Marta Martinez, Roberto Marabini
Author-email: scipion@cnb.csic.es
License: UNKNOWN
Keywords: scipion cryoem imageprocessing scipion-3.0
Platform: UNKNOWN
Classifier: Development Status :: 3 - Alpha
Classifier: License :: OSI Approved :: GNU General Public License v3 (GPLv3)
Classifier: Programming Language :: Python :: 3
Requires-Dist: scipion-em
